roombapy/__init__.py
roombapy/cli.py
roombapy/const.py
roombapy/discovery.py
roombapy/getpassword.py
roombapy/py.typed
roombapy/remote_client.py
roombapy/roomba.py
roombapy/roomba_factory.py
roombapy/roomba_info.py
roombapy-1.9.1.dist-info/LICENSE
roombapy-1.9.1.dist-info/METADATA
roombapy-1.9.1.dist-info/WHEEL
roombapy-1.9.1.dist-info/entry_points.txt
roombapy-1.9.1.dist-info/RECORD
