Metadata-Version: 2.3
Name: roombapy
Version: 1.9.1
Summary: Python program and library to control Wi-Fi enabled iRobot Roombas
License: MIT
Author: Philipp Schmitt
Author-email: philipp@schmitt.co
Requires-Python: >=3.10,<4.0
Classifier: License :: OSI Approved :: MIT License
Classifier: Programming Language :: Python :: 3
Classifier: Programming Language :: Python :: 3.10
Classifier: Programming Language :: Python :: 3.11
Classifier: Programming Language :: Python :: 3.12
Classifier: Programming Language :: Python :: 3.13
Classifier: Topic :: Software Development
Classifier: Topic :: Software Development :: Libraries
Classifier: Topic :: Software Development :: Libraries :: Python Modules
Classifier: Topic :: System :: Networking
Provides-Extra: cli
Requires-Dist: click (>=8.1,<9.0) ; extra == "cli"
Requires-Dist: mashumaro (>=3.12,<4.0)
Requires-Dist: orjson (>=3.9.13)
Requires-Dist: paho-mqtt (>=1.6.1,<3.0.0)
Requires-Dist: tabulate (>=0.9,<0.10) ; extra == "cli"
Requires-Dist: typing_extensions (>=4.12.0)
Project-URL: Repository, https://github.com/pschmitt/roombapy
